{
  "capturedAt": "2026-05-29T06:04:52-03:00",
  "rows": [
    {
      "origem": "AR",
      "sexo": "FEMEA",
      "qtdCompra": 41100,
      "pesoMedioKg": 500.67,
      "precoMedioUSDKg": 4.37
    },
    {
      "origem": "AR",
      "sexo": "MACHO",
      "qtdCompra": 46993,
      "pesoMedioKg": 515.2,
      "precoMedioUSDKg": 5.57
    },
    {
      "origem": "BR",
      "sexo": "FEMEA",
      "qtdCompra": 99625,
      "pesoMedioKg": 223.46,
      "precoMedioUSDKg": 4.61,
      "valorKgBaseUSD": 4.58
    },
    {
      "origem": "BR",
      "sexo": "MACHO",
      "qtdCompra": 154261,
      "pesoMedioKg": 287.92,
      "precoMedioUSDKg": 4.72,
      "valorKgBaseUSD": 4.68
    },
    {
      "origem": "CO",
      "sexo": "FEMEA",
      "qtdCompra": 14087,
      "pesoMedioKg": 307.46,
      "precoMedioUSDKg": 4.43
    },
    {
      "origem": "CO",
      "sexo": "MACHO",
      "qtdCompra": 11239,
      "pesoMedioKg": 394.02,
      "precoMedioUSDKg": 4.15
    },
    {
      "origem": "PY",
      "sexo": "FEMEA",
      "qtdCompra": 26540,
      "pesoMedioKg": 193.49,
      "precoMedioUSDKg": 4.84,
      "valorKgBaseUSD": 4.75
    },
    {
      "origem": "PY",
      "sexo": "MACHO",
      "qtdCompra": 47392,
      "pesoMedioKg": 208.36,
      "precoMedioUSDKg": 5.0,
      "valorKgBaseUSD": 4.84
    },
    {
      "origem": "UY",
      "sexo": "FEMEA",
      "qtdCompra": 1621,
      "pesoMedioKg": 275.41,
      "precoMedioUSDKg": 5.23,
      "valorKgBaseUSD": 4.79
    },
    {
      "origem": "UY",
      "sexo": "MACHO",
      "qtdCompra": 1591,
      "pesoMedioKg": 284.47,
      "precoMedioUSDKg": 5.61,
      "valorKgBaseUSD": 4.21
    }
  ],
  "totals": {
    "qtdCompra": 444449,
    "pesoMedioKg": 306.3,
    "precoMedioUSDKg": 4.8,
    "valorKgBaseUSD": 4.69
  },
  "source": {
    "module": "Compras Now",
    "breadcrumb": "DUX > Minerva Reports > Relatorios de Controle > Compras Now"
  },
  "originTotals": {
    "AR": {
      "qtdCompra": 88093,
      "pesoMedioKg": 508.42,
      "precoMedioUSDKg": 5.11
    },
    "BR": {
      "qtdCompra": 253886,
      "pesoMedioKg": 262.62,
      "precoMedioUSDKg": 4.68,
      "valorKgBaseUSD": 4.64
    },
    "CO": {
      "qtdCompra": 25326,
      "pesoMedioKg": 345.88,
      "precoMedioUSDKg": 4.3
    },
    "PY": {
      "qtdCompra": 73932,
      "pesoMedioKg": 203.02,
      "precoMedioUSDKg": 4.95,
      "valorKgBaseUSD": 4.81
    },
    "UY": {
      "qtdCompra": 3212,
      "pesoMedioKg": 279.9,
      "precoMedioUSDKg": 5.42,
      "valorKgBaseUSD": 4.77
    }
  },
  "period": "last30",
  "periodFrom": "2026-04-28T00:00:00-03:00",
  "periodTo": "2026-05-28T23:59:59-03:00",
  "periodLabel": "Ultimos 30 dias (28/04 - 28/05)",
  "screenshotPath": "data/screenshots/last30.png"
}