{
  "capturedAt": "2026-06-26T06:02:19-03:00",
  "rows": [
    {
      "origem": "AR",
      "sexo": "FEMEA",
      "qtdCompra": 11097,
      "pesoMedioKg": 510.28,
      "precoMedioUSDKg": 4.0
    },
    {
      "origem": "AR",
      "sexo": "MACHO",
      "qtdCompra": 8111,
      "pesoMedioKg": 1668.88,
      "precoMedioUSDKg": 5.19
    },
    {
      "origem": "BR",
      "sexo": "FEMEA",
      "qtdCompra": 11076,
      "pesoMedioKg": 221.56,
      "precoMedioUSDKg": 4.28,
      "valorKgBaseUSD": 4.12
    },
    {
      "origem": "BR",
      "sexo": "MACHO",
      "qtdCompra": 21748,
      "pesoMedioKg": 283.36,
      "precoMedioUSDKg": 4.51,
      "valorKgBaseUSD": 4.21
    },
    {
      "origem": "CO",
      "sexo": "FEMEA",
      "qtdCompra": 3295,
      "pesoMedioKg": 311.53,
      "precoMedioUSDKg": 4.48
    },
    {
      "origem": "CO",
      "sexo": "MACHO",
      "qtdCompra": 3331,
      "pesoMedioKg": 435.99,
      "precoMedioUSDKg": 4.67
    },
    {
      "origem": "PY",
      "sexo": "FEMEA",
      "qtdCompra": 6663,
      "pesoMedioKg": 190.05,
      "precoMedioUSDKg": 5.03,
      "valorKgBaseUSD": 4.94
    },
    {
      "origem": "PY",
      "sexo": "MACHO",
      "qtdCompra": 13003,
      "pesoMedioKg": 209.41,
      "precoMedioUSDKg": 5.23,
      "valorKgBaseUSD": 5.06
    },
    {
      "origem": "UY",
      "sexo": "FEMEA",
      "qtdCompra": 655,
      "pesoMedioKg": 235.66,
      "precoMedioUSDKg": 5.05
    },
    {
      "origem": "UY",
      "sexo": "MACHO",
      "qtdCompra": 547,
      "pesoMedioKg": 296.65,
      "precoMedioUSDKg": 5.82
    }
  ],
  "totals": {
    "qtdCompra": 79526,
    "pesoMedioKg": 435.08,
    "precoMedioUSDKg": 4.71,
    "valorKgBaseUSD": 4.49
  },
  "source": {
    "module": "Compras Now",
    "breadcrumb": "DUX > Minerva Reports > Relatorios de Controle > Compras Now"
  },
  "originTotals": {
    "AR": {
      "qtdCompra": 19208,
      "pesoMedioKg": 999.52,
      "precoMedioUSDKg": 4.6
    },
    "BR": {
      "qtdCompra": 32824,
      "pesoMedioKg": 262.5,
      "precoMedioUSDKg": 4.44,
      "valorKgBaseUSD": 4.18
    },
    "CO": {
      "qtdCompra": 6626,
      "pesoMedioKg": 374.1,
      "precoMedioUSDKg": 4.58
    },
    "PY": {
      "qtdCompra": 19666,
      "pesoMedioKg": 202.85,
      "precoMedioUSDKg": 5.17,
      "valorKgBaseUSD": 5.02
    },
    "UY": {
      "qtdCompra": 1202,
      "pesoMedioKg": 263.42,
      "precoMedioUSDKg": 5.43
    }
  },
  "period": "last7",
  "periodFrom": "2026-06-18T00:00:00-03:00",
  "periodTo": "2026-06-25T23:59:59-03:00",
  "periodLabel": "Ultimos 7 dias (18/06 - 25/06)",
  "screenshotPath": "data/screenshots/last7.png"
}