{
  "capturedAt": "2026-06-09T14:02:20-03:00",
  "rows": [
    {
      "origem": "AR",
      "sexo": "FEMEA",
      "qtdCompra": 1190,
      "pesoMedioKg": 524.82,
      "precoMedioUSDKg": 4.39
    },
    {
      "origem": "AR",
      "sexo": "MACHO",
      "qtdCompra": 588,
      "pesoMedioKg": 573.21,
      "precoMedioUSDKg": 5.33
    },
    {
      "origem": "BR",
      "sexo": "FEMEA",
      "qtdCompra": 2166,
      "pesoMedioKg": 221.5,
      "precoMedioUSDKg": 4.24,
      "valorKgBaseUSD": 4.35
    },
    {
      "origem": "BR",
      "sexo": "MACHO",
      "qtdCompra": 3548,
      "pesoMedioKg": 294.91,
      "precoMedioUSDKg": 4.52,
      "valorKgBaseUSD": 4.5
    },
    {
      "origem": "CO",
      "sexo": "FEMEA",
      "qtdCompra": 1146,
      "pesoMedioKg": 346.77,
      "precoMedioUSDKg": 4.31
    },
    {
      "origem": "CO",
      "sexo": "MACHO",
      "qtdCompra": 420,
      "pesoMedioKg": 319.29,
      "precoMedioUSDKg": 5.01
    },
    {
      "origem": "PY",
      "sexo": "FEMEA",
      "qtdCompra": 622,
      "pesoMedioKg": 204.12,
      "precoMedioUSDKg": 4.86,
      "valorKgBaseUSD": 4.86
    },
    {
      "origem": "PY",
      "sexo": "MACHO",
      "qtdCompra": 866,
      "pesoMedioKg": 209.55,
      "precoMedioUSDKg": 5.13,
      "valorKgBaseUSD": 5.0
    },
    {
      "origem": "UY",
      "sexo": "FEMEA",
      "qtdCompra": 54,
      "pesoMedioKg": 311.7,
      "precoMedioUSDKg": 5.86
    },
    {
      "origem": "UY",
      "sexo": "MACHO",
      "qtdCompra": 381,
      "pesoMedioKg": 340.91,
      "precoMedioUSDKg": 6.09
    }
  ],
  "totals": {
    "qtdCompra": 10981,
    "pesoMedioKg": 316.4,
    "precoMedioUSDKg": 4.67,
    "valorKgBaseUSD": 4.54
  },
  "source": {
    "module": "Compras Now",
    "breadcrumb": "DUX > Minerva Reports > Relatorios de Controle > Compras Now"
  },
  "originTotals": {
    "AR": {
      "qtdCompra": 1778,
      "pesoMedioKg": 540.82,
      "precoMedioUSDKg": 4.76
    },
    "BR": {
      "qtdCompra": 5714,
      "pesoMedioKg": 267.08,
      "precoMedioUSDKg": 4.42,
      "valorKgBaseUSD": 4.45
    },
    "CO": {
      "qtdCompra": 1566,
      "pesoMedioKg": 339.4,
      "precoMedioUSDKg": 4.53
    },
    "PY": {
      "qtdCompra": 1488,
      "pesoMedioKg": 207.28,
      "precoMedioUSDKg": 5.02,
      "valorKgBaseUSD": 4.94
    },
    "UY": {
      "qtdCompra": 435,
      "pesoMedioKg": 337.28,
      "precoMedioUSDKg": 6.06
    }
  },
  "period": "today",
  "periodFrom": "2026-06-09T00:00:00-03:00",
  "periodTo": "2026-06-09T23:59:59-03:00",
  "periodLabel": "Hoje (09/06)",
  "screenshotPath": "data/screenshots/today.png"
}