{
  "capturedAt": "2026-06-22T16:01:46-03:00",
  "rows": [
    {
      "origem": "AR",
      "sexo": "FEMEA",
      "qtdCompra": 783,
      "pesoMedioKg": 660.7,
      "precoMedioUSDKg": 4.49
    },
    {
      "origem": "AR",
      "sexo": "MACHO",
      "qtdCompra": 1142,
      "pesoMedioKg": 510.33,
      "precoMedioUSDKg": 5.31
    },
    {
      "origem": "BR",
      "sexo": "FEMEA",
      "qtdCompra": 1353,
      "pesoMedioKg": 212.59,
      "precoMedioUSDKg": 4.18,
      "valorKgBaseUSD": 4.23
    },
    {
      "origem": "BR",
      "sexo": "MACHO",
      "qtdCompra": 2597,
      "pesoMedioKg": 278.46,
      "precoMedioUSDKg": 4.48,
      "valorKgBaseUSD": 4.43
    },
    {
      "origem": "CO",
      "sexo": "FEMEA",
      "qtdCompra": 742,
      "pesoMedioKg": 246.21,
      "precoMedioUSDKg": 4.85
    },
    {
      "origem": "CO",
      "sexo": "MACHO",
      "qtdCompra": 448,
      "pesoMedioKg": 335.87,
      "precoMedioUSDKg": 4.93
    },
    {
      "origem": "PY",
      "sexo": "FEMEA",
      "qtdCompra": 55,
      "pesoMedioKg": 185.45,
      "precoMedioUSDKg": 4.81,
      "valorKgBaseUSD": 4.85
    },
    {
      "origem": "PY",
      "sexo": "MACHO",
      "qtdCompra": 977,
      "pesoMedioKg": 210.0,
      "precoMedioUSDKg": 5.15,
      "valorKgBaseUSD": 5.05
    }
  ],
  "totals": {
    "qtdCompra": 8097,
    "pesoMedioKg": 328.45,
    "precoMedioUSDKg": 4.72,
    "valorKgBaseUSD": 4.51
  },
  "source": {
    "module": "Compras Now",
    "breadcrumb": "DUX > Minerva Reports > Relatorios de Controle > Compras Now"
  },
  "originTotals": {
    "AR": {
      "qtdCompra": 1925,
      "pesoMedioKg": 571.5,
      "precoMedioUSDKg": 5.01
    },
    "BR": {
      "qtdCompra": 3950,
      "pesoMedioKg": 255.9,
      "precoMedioUSDKg": 4.38,
      "valorKgBaseUSD": 4.38
    },
    "CO": {
      "qtdCompra": 1190,
      "pesoMedioKg": 279.96,
      "precoMedioUSDKg": 4.88
    },
    "PY": {
      "qtdCompra": 1032,
      "pesoMedioKg": 208.69,
      "precoMedioUSDKg": 5.14,
      "valorKgBaseUSD": 5.04
    }
  },
  "period": "today",
  "periodFrom": "2026-06-22T00:00:00-03:00",
  "periodTo": "2026-06-22T23:59:59-03:00",
  "periodLabel": "Hoje (22/06)",
  "screenshotPath": "data/screenshots/today.png"
}