{
  "capturedAt": "2026-06-15T09:02:22-03:00",
  "rows": [
    {
      "origem": "BR",
      "sexo": "FEMEA",
      "qtdCompra": 313,
      "pesoMedioKg": 219.17,
      "precoMedioUSDKg": 4.26
    },
    {
      "origem": "BR",
      "sexo": "MACHO",
      "qtdCompra": 2018,
      "pesoMedioKg": 300.27,
      "precoMedioUSDKg": 4.69,
      "valorKgBaseUSD": 4.71
    },
    {
      "origem": "PY",
      "sexo": "FEMEA",
      "qtdCompra": 349,
      "pesoMedioKg": 210.0,
      "precoMedioUSDKg": 5.16,
      "valorKgBaseUSD": 5.0
    },
    {
      "origem": "PY",
      "sexo": "MACHO",
      "qtdCompra": 803,
      "pesoMedioKg": 210.0,
      "precoMedioUSDKg": 5.21,
      "valorKgBaseUSD": 5.05
    }
  ],
  "totals": {
    "qtdCompra": 3483,
    "pesoMedioKg": 263.13,
    "precoMedioUSDKg": 4.83,
    "valorKgBaseUSD": 4.8
  },
  "source": {
    "module": "Compras Now",
    "breadcrumb": "DUX > Minerva Reports > Relatorios de Controle > Compras Now"
  },
  "originTotals": {
    "BR": {
      "qtdCompra": 2331,
      "pesoMedioKg": 289.38,
      "precoMedioUSDKg": 4.63,
      "valorKgBaseUSD": 4.71
    },
    "PY": {
      "qtdCompra": 1152,
      "pesoMedioKg": 210.0,
      "precoMedioUSDKg": 5.19,
      "valorKgBaseUSD": 5.02
    }
  },
  "period": "today",
  "periodFrom": "2026-06-15T00:00:00-03:00",
  "periodTo": "2026-06-15T23:59:59-03:00",
  "periodLabel": "Hoje (15/06)",
  "screenshotPath": "data/screenshots/today.png"
}