{
  "capturedAt": "2026-05-28T10:39:54-03:00",
  "rows": [
    {
      "origem": "AR",
      "sexo": "FEMEA",
      "qtdCompra": 378,
      "pesoMedioKg": 520.68,
      "precoMedioUSDKg": 3.95
    },
    {
      "origem": "AR",
      "sexo": "MACHO",
      "qtdCompra": 542,
      "pesoMedioKg": 520.85,
      "precoMedioUSDKg": 5.52
    },
    {
      "origem": "BR",
      "sexo": "FEMEA",
      "qtdCompra": 835,
      "pesoMedioKg": 212.48,
      "precoMedioUSDKg": 4.5,
      "valorKgBaseUSD": 4.45
    },
    {
      "origem": "BR",
      "sexo": "MACHO",
      "qtdCompra": 2214,
      "pesoMedioKg": 280.23,
      "precoMedioUSDKg": 4.88,
      "valorKgBaseUSD": 4.65
    },
    {
      "origem": "CO",
      "sexo": "FEMEA",
      "qtdCompra": 228,
      "pesoMedioKg": 385.81,
      "precoMedioUSDKg": 2.87
    },
    {
      "origem": "CO",
      "sexo": "MACHO",
      "qtdCompra": 15,
      "pesoMedioKg": 215.0,
      "precoMedioUSDKg": 5.62
    },
    {
      "origem": "PY",
      "sexo": "FEMEA",
      "qtdCompra": 81,
      "pesoMedioKg": 188.89,
      "precoMedioUSDKg": 4.75,
      "valorKgBaseUSD": 4.77
    },
    {
      "origem": "PY",
      "sexo": "MACHO",
      "qtdCompra": 2,
      "pesoMedioKg": 210.0,
      "precoMedioUSDKg": 4.85,
      "valorKgBaseUSD": 4.9
    }
  ],
  "totals": {
    "qtdCompra": 4295,
    "pesoMedioKg": 322.21,
    "precoMedioUSDKg": 4.78,
    "valorKgBaseUSD": 4.61
  },
  "source": {
    "module": "Compras Now",
    "breadcrumb": "DUX > Minerva Reports > Relatorios de Controle > Compras Now"
  },
  "originTotals": {
    "AR": {
      "qtdCompra": 920,
      "pesoMedioKg": 520.78,
      "precoMedioUSDKg": 5.03
    },
    "BR": {
      "qtdCompra": 3049,
      "pesoMedioKg": 261.68,
      "precoMedioUSDKg": 4.78,
      "valorKgBaseUSD": 4.6
    },
    "CO": {
      "qtdCompra": 243,
      "pesoMedioKg": 375.26,
      "precoMedioUSDKg": 3.21
    },
    "PY": {
      "qtdCompra": 83,
      "pesoMedioKg": 189.4,
      "precoMedioUSDKg": 4.75,
      "valorKgBaseUSD": 4.77
    }
  },
  "period": "today",
  "periodFrom": "2026-05-28T00:00:00-03:00",
  "periodTo": "2026-05-28T23:59:59-03:00",
  "periodLabel": "Hoje (28/05)",
  "screenshotPath": "data/screenshots/today.png"
}