{
  "capturedAt": "2026-06-22T09:02:21-03:00",
  "rows": [
    {
      "origem": "AR",
      "sexo": "FEMEA",
      "qtdCompra": 220,
      "pesoMedioKg": 1093.41,
      "precoMedioUSDKg": 4.46
    },
    {
      "origem": "AR",
      "sexo": "MACHO",
      "qtdCompra": 208,
      "pesoMedioKg": 501.92,
      "precoMedioUSDKg": 5.35
    },
    {
      "origem": "BR",
      "sexo": "FEMEA",
      "qtdCompra": 361,
      "pesoMedioKg": 209.35,
      "precoMedioUSDKg": 4.1,
      "valorKgBaseUSD": 4.2
    },
    {
      "origem": "BR",
      "sexo": "MACHO",
      "qtdCompra": 520,
      "pesoMedioKg": 286.58,
      "precoMedioUSDKg": 4.38
    },
    {
      "origem": "CO",
      "sexo": "FEMEA",
      "qtdCompra": 384,
      "pesoMedioKg": 270.72,
      "precoMedioUSDKg": 4.43
    },
    {
      "origem": "CO",
      "sexo": "MACHO",
      "qtdCompra": 196,
      "pesoMedioKg": 235.38,
      "precoMedioUSDKg": 5.64
    }
  ],
  "totals": {
    "qtdCompra": 1889,
    "pesoMedioKg": 380.96,
    "precoMedioUSDKg": 4.64,
    "valorKgBaseUSD": 4.2
  },
  "source": {
    "module": "Compras Now",
    "breadcrumb": "DUX > Minerva Reports > Relatorios de Controle > Compras Now"
  },
  "originTotals": {
    "AR": {
      "qtdCompra": 428,
      "pesoMedioKg": 805.96,
      "precoMedioUSDKg": 4.93
    },
    "BR": {
      "qtdCompra": 881,
      "pesoMedioKg": 254.93,
      "precoMedioUSDKg": 4.27,
      "valorKgBaseUSD": 4.2
    },
    "CO": {
      "qtdCompra": 580,
      "pesoMedioKg": 258.78,
      "precoMedioUSDKg": 4.92
    }
  },
  "period": "today",
  "periodFrom": "2026-06-22T00:00:00-03:00",
  "periodTo": "2026-06-22T23:59:59-03:00",
  "periodLabel": "Hoje (22/06)",
  "screenshotPath": "data/screenshots/today.png"
}